<http-page executeResourcesDynamically="false"
    name="/jpetstore/shop/signon.shtml" playRequestsSequentially="false"
    recordedArtifactZipFileName="team/vus/@d@a@v@i@d/%resources%/recorded-artifacts/79a2e6f4-68aa-40aa-a1eb-61b2c0b22c5c.zip"
    slaProfileEnabled="false" thinkTime="2207"
    thinkTimeMode="MODE_SIMPLE_THINK_TIME" thinkTimeRangeEnd=""
    thinkTimeRangeStart="" uid="79a2e6f4-68aa-40aa-a1eb-61b2c0b22c5c">
    <embedded-action>04504605-e538-4c99-9cdf-aca14304aee3</embedded-action>
    <embedded-action>6509945f-c713-41d3-95a7-f5a50bef48b7</embedded-action>
    <embedded-action>583bd8f8-221c-4777-b091-4879c006992d</embedded-action>
    <embedded-action>c7281585-594c-4439-8693-72948f138057</embedded-action>
    <screenshotFileDescription>recorded-screenshots/sc_c286b15a-a131-48f4-bc7b-72b4b140732b.jpg</screenshotFileDescription>
</http-page>
<http-action actionType="1" contentType="text/html;charset=ISO-8859-1"
    extractorInjectPathPolicy="2" extractorPathPolicy="1"
    followRedirects="false" generatedByClient="false"
    linkExtractorSeveralMatchOccurrence="1"
    linkExtractorSeveralMatchPolicy="1" linkExtractorType="6"
    method="POST" name="/jpetstore/shop/signon.shtml"
    path="/jpetstore/shop/signon.shtml" postCharset="iso-8859-1"
    postType="1"
    recordedArtifactZipFileName="team/vus/@d@a@v@i@d/%resources%/recorded-artifacts/79a2e6f4-68aa-40aa-a1eb-61b2c0b22c5c.zip"
    recordedResponseCode="200"
    refererUid="0a7528c5-9dce-4ad6-84bc-8a2dfe29834a"
    responseSize="6530" serverUid="practise.neotys.com"
    slaProfileEnabled="false" uid="04504605-e538-4c99-9cdf-aca14304aee3" useKeepAlive="false">
    <binaryPostContentBase64><![CDATA[dXNlcm5hbWU9ajJlZSZwYXNzd29yZD1qMmVlJng9MjYmeT03]]></binaryPostContentBase64>
    <responsePageFileDescription>recorded-responses/res_bc13bdb5-1e6d-4c40-ad1c-cbc3bb38ada5.html</responsePageFileDescription>
    <requestContentFileDescription>recorded-requests/req_bc13bdb5-1e6d-4c40-ad1c-cbc3bb38ada5.txt</requestContentFileDescription>
    <parameter encodeName="true" encodeValue="true" name="username"
        recordRawValue="j2ee" separator="=" value="j2ee" valueMode="USE_VALUE"/>
    <parameter encodeName="true" encodeValue="true" name="password"
        recordRawValue="j2ee" separator="=" value="j2ee" valueMode="USE_VALUE"/>
    <parameter encodeName="true" encodeValue="true" name="x"
        recordRawValue="26" separator="=" value="26" valueMode="USE_VALUE"/>
    <parameter encodeName="true" encodeValue="true" name="y"
        recordRawValue="7" separator="=" value="7" valueMode="USE_VALUE"/>
    <header name="Accept" value="text/html, application/xhtml+xml, */*"/>
    <header name="Accept-Encoding" value="gzip, deflate"/>
    <header name="Accept-Language" value="en-US"/>
    <header name="Content-Type" value="application/x-www-form-urlencoded"/>
    <header name="Cookie" value="JSESSIONID=84940372B629D6277305E9AB3228B2F2"/>
    <header name="DNT" value="1"/>
    <header name="Host" value="52.206.109.101"/>
    <header name="Pragma" value="no-cache"/>
    <header name="Referer" value="http://52.206.109.101/jpetstore/shop/newOrderForm.shtml"/>
    <header name="User-Agent" value="Mozilla/5.0 (Windows NT 6.1; WOW64; Trident/7.0; rv:11.0) like Gecko"/>
    <responseHeaders>HTTP/1.1 200 OK&#xd;
Date: Mon, 19 Jun 2017 14:39:46 GMT&#xd;
Server: Apache/2.2.31 (Amazon)&#xd;
Content-Length: 6530&#xd;
Connection: close&#xd;
Content-Type: text/html;charset=ISO-8859-1</responseHeaders>
    <record-html-infos extractorName="accountBean"
        extractorOccurence="2" extractorRegExp="false" htmlType="2"/>
</http-action>
<http-action actionType="1" contentType="image/gif"
    extractorInjectPathPolicy="2" extractorPathPolicy="1"
    followRedirects="false" generatedByClient="false"
    linkExtractorSeveralMatchOccurrence="1"
    linkExtractorSeveralMatchPolicy="1" linkExtractorType="6"
    method="GET" name="/jpetstore/images/my_account.gif"
    path="/jpetstore/images/my_account.gif" postType="1"
    recordedArtifactZipFileName="team/vus/@d@a@v@i@d/%resources%/recorded-artifacts/79a2e6f4-68aa-40aa-a1eb-61b2c0b22c5c.zip"
    recordedResponseCode="200" responseSize="0"
    serverUid="practise.neotys.com" slaProfileEnabled="false"
    uid="6509945f-c713-41d3-95a7-f5a50bef48b7" useKeepAlive="false">
    <responsePageFileDescription>recorded-responses/res_6509945f-c713-41d3-95a7-f5a50bef48b7.gif</responsePageFileDescription>
    <requestContentFileDescription>recorded-requests/req_f1ecb13c-00ba-4225-9541-c6afb5726620.txt</requestContentFileDescription>
    <header name="Accept" value="image/png, image/svg+xml, image/*;q=0.8, */*;q=0.5"/>
    <header name="Accept-Encoding" value="gzip, deflate"/>
    <header name="Accept-Language" value="en-US"/>
    <header name="Content-Type" value="application/x-www-form-urlencoded"/>
    <header name="Cookie" value="JSESSIONID=84940372B629D6277305E9AB3228B2F2"/>
    <header name="DNT" value="1"/>
    <header name="Host" value="52.206.109.101"/>
    <header name="Referer" value="http://52.206.109.101/jpetstore/shop/signon.shtml"/>
    <header name="User-Agent" value="Mozilla/5.0 (Windows NT 6.1; WOW64; Trident/7.0; rv:11.0) like Gecko"/>
    <responseHeaders>HTTP/1.1 200 OK&#xd;
Date: Mon, 19 Jun 2017 14:39:46 GMT&#xd;
Server: Apache/2.2.31 (Amazon)&#xd;
Accept-Ranges: bytes&#xd;
ETag: W/"455-1088130660000"&#xd;
Last-Modified: Fri, 25 Jun 2004 02:31:00 GMT&#xd;
Content-Length: 455&#xd;
Connection: close&#xd;
Content-Type: image/gif</responseHeaders>
    <record-html-infos extractorRegExp="false" htmlType="0"/>
</http-action>
<http-action actionType="1" contentType="image/gif"
    extractorInjectPathPolicy="2" extractorPathPolicy="1"
    followRedirects="false" generatedByClient="false"
    linkExtractorSeveralMatchOccurrence="1"
    linkExtractorSeveralMatchPolicy="1" linkExtractorType="6"
    method="GET" name="/jpetstore/images/sign-out.gif"
    path="/jpetstore/images/sign-out.gif" postType="1"
    recordedArtifactZipFileName="team/vus/@d@a@v@i@d/%resources%/recorded-artifacts/79a2e6f4-68aa-40aa-a1eb-61b2c0b22c5c.zip"
    recordedResponseCode="200" responseSize="0"
    serverUid="practise.neotys.com" slaProfileEnabled="false"
    uid="583bd8f8-221c-4777-b091-4879c006992d" useKeepAlive="false">
    <responsePageFileDescription>recorded-responses/res_583bd8f8-221c-4777-b091-4879c006992d.gif</responsePageFileDescription>
    <requestContentFileDescription>recorded-requests/req_f1fb28c3-9487-4a7d-a6dd-d843123f682b.txt</requestContentFileDescription>
    <header name="Accept" value="image/png, image/svg+xml, image/*;q=0.8, */*;q=0.5"/>
    <header name="Accept-Encoding" value="gzip, deflate"/>
    <header name="Accept-Language" value="en-US"/>
    <header name="Content-Type" value="application/x-www-form-urlencoded"/>
    <header name="Cookie" value="JSESSIONID=84940372B629D6277305E9AB3228B2F2"/>
    <header name="DNT" value="1"/>
    <header name="Host" value="52.206.109.101"/>
    <header name="Referer" value="http://52.206.109.101/jpetstore/shop/signon.shtml"/>
    <header name="User-Agent" value="Mozilla/5.0 (Windows NT 6.1; WOW64; Trident/7.0; rv:11.0) like Gecko"/>
    <responseHeaders>HTTP/1.1 200 OK&#xd;
Date: Mon, 19 Jun 2017 14:39:46 GMT&#xd;
Server: Apache/2.2.31 (Amazon)&#xd;
Accept-Ranges: bytes&#xd;
ETag: W/"290-1088130660000"&#xd;
Last-Modified: Fri, 25 Jun 2004 02:31:00 GMT&#xd;
Content-Length: 290&#xd;
Connection: close&#xd;
Content-Type: image/gif</responseHeaders>
    <record-html-infos extractorRegExp="false" htmlType="0"/>
</http-action>
<http-action actionType="1" contentType="image/gif"
    extractorInjectPathPolicy="2" extractorPathPolicy="1"
    followRedirects="false" generatedByClient="false"
    linkExtractorSeveralMatchOccurrence="1"
    linkExtractorSeveralMatchPolicy="1" linkExtractorType="6"
    method="GET" name="/jpetstore/images/banner_dogs.gif"
    path="/jpetstore/images/banner_dogs.gif" postType="1"
    recordedArtifactZipFileName="team/vus/@d@a@v@i@d/%resources%/recorded-artifacts/79a2e6f4-68aa-40aa-a1eb-61b2c0b22c5c.zip"
    recordedResponseCode="200" responseSize="0"
    serverUid="practise.neotys.com" slaProfileEnabled="false"
    uid="c7281585-594c-4439-8693-72948f138057" useKeepAlive="false">
    <responsePageFileDescription>recorded-responses/res_c7281585-594c-4439-8693-72948f138057.gif</responsePageFileDescription>
    <requestContentFileDescription>recorded-requests/req_c5448a86-d7bb-4f38-bd2c-9b260cf50bbc.txt</requestContentFileDescription>
    <header name="Accept" value="image/png, image/svg+xml, image/*;q=0.8, */*;q=0.5"/>
    <header name="Accept-Encoding" value="gzip, deflate"/>
    <header name="Accept-Language" value="en-US"/>
    <header name="Content-Type" value="application/x-www-form-urlencoded"/>
    <header name="Cookie" value="JSESSIONID=84940372B629D6277305E9AB3228B2F2"/>
    <header name="DNT" value="1"/>
    <header name="Host" value="52.206.109.101"/>
    <header name="Referer" value="http://52.206.109.101/jpetstore/shop/signon.shtml"/>
    <header name="User-Agent" value="Mozilla/5.0 (Windows NT 6.1; WOW64; Trident/7.0; rv:11.0) like Gecko"/>
    <responseHeaders>HTTP/1.1 200 OK&#xd;
Date: Mon, 19 Jun 2017 14:39:46 GMT&#xd;
Server: Apache/2.2.31 (Amazon)&#xd;
Accept-Ranges: bytes&#xd;
ETag: W/"6161-1088130660000"&#xd;
Last-Modified: Fri, 25 Jun 2004 02:31:00 GMT&#xd;
Content-Length: 6161&#xd;
Connection: close&#xd;
Content-Type: image/gif</responseHeaders>
    <record-html-infos extractorRegExp="false" htmlType="0"/>
</http-action>
